setup.py
ezsettings/__init__.py
ezsettings/settings.py
ezsettings/tests.py
ezsettings.egg-info/PKG-INFO
ezsettings.egg-info/SOURCES.txt
ezsettings.egg-info/dependency_links.txt
ezsettings.egg-info/not-zip-safe
ezsettings.egg-info/top_level.txt