Metadata-Version: 1.0
Name: ezsettings
Version: 1.1
Summary: simple setings management
Home-page: http://github.com/samyzaf/ezsettings
Author: Samy Zafrany
Author-email: admin@samyzaf.com
License: MIT
Platform: UNKNOWN
